mso/__init__.py
mso/api.py
mso/base_model.py
mso/config.py
mso/connection.py
mso/generator.py
mso/mongo_helpers.py
mso/py.typed
mso/read_only_model.py
mso/schema_loader.py
mso/threading_cleanup_warning.py
mso/utils.py
mso-1.0.86.dist-info/METADATA
mso-1.0.86.dist-info/WHEEL
mso-1.0.86.dist-info/licenses/LICENSE
mso-1.0.86.dist-info/RECORD
