Metadata-Version: 2.4
Name: MSO
Version: 1.0.86
Summary: MongoDB Schema Object - A ODM from Mongo DB JSON validation schema
License: Creative Commons Attribution-NonCommercial-ShareAlike 4.0 International
License-File: LICENSE
Keywords: ORM,MongoDB,ODM,JSON,Schema,Validation,Object,Document,Model
Author: Charles Beyor
Requires-Python: >=3.12,<4.0
Classifier: Development Status :: 4 - Beta
Classifier: Intended Audience :: Developers
Classifier: License :: Other/Proprietary License
Classifier: Operating System :: OS Independent
Classifier: Programming Language :: Python :: 3
Classifier: Programming Language :: Python :: 3.12
Classifier: Programming Language :: Python :: 3.13
Classifier: Programming Language :: Python :: 3.14
Classifier: Topic :: Database
Classifier: Topic :: Software Development :: Libraries
Requires-Dist: fastapi (>=0.110.0,<0.111.0)
Requires-Dist: pydantic (>=2.6.0,<3.0.0)
Requires-Dist: pymongo (>=4.0,<5.0)
Requires-Dist: python-dateutil (>=2.9.0,<3.0.0)
Requires-Dist: uvicorn[standard] (>=0.27.0,<0.28.0)
Project-URL: Pypi, https://pypi.org/project/MSO/
Project-URL: Repository, https://github.com/chuckbeyor101/MSO-Mongo-Schema-Object-Library
Project-URL: Reddit, https://www.reddit.com/r/MSO_Mongo_Python_ORM/
